BotsOnRails/__about__.py
BotsOnRails/__init__.py
BotsOnRails/decorators.py
BotsOnRails/nodes.py
BotsOnRails/rails.py
BotsOnRails/stores.py
BotsOnRails/types.py
BotsOnRails/utils.py
botsonrails-0.1.2.dist-info/METADATA
botsonrails-0.1.2.dist-info/WHEEL
botsonrails-0.1.2.dist-info/licenses/LICENSE.txt
botsonrails-0.1.2.dist-info/RECORD
