Metadata-Version: 2.3
Name: BotsOnRails
Version: 0.1.2
Summary: BotsOnRails makes it easy to write LLM-controlled programs without outsourcing all of the logic and decisions to stochastic models. It facilitates the seamless integration of function-based nodes into an execution tree, enabling conditional and sequential task execution tailored to complex, resumable processing flows.
Project-URL: Documentation, https://github.com/JSv4/BotsOnRails#readme
Project-URL: Issues, https://github.com/JSv4/BotsOnRails/issues
Project-URL: Source, https://github.com/JSv4/BotsOnRails
Author-email: JSv4 <scrudato@umich.edu>
License-Expression: MIT
License-File: LICENSE.txt
Classifier: Development Status :: 4 - Beta
Classifier: Programming Language :: Python
Classifier: Programming Language :: Python :: 3.9
Classifier: Programming Language :: Python :: 3.10
Classifier: Programming Language :: Python :: 3.11
Classifier: Programming Language :: Python :: 3.12
Classifier: Programming Language :: Python :: Implementation :: CPython
Classifier: Programming Language :: Python :: Implementation :: PyPy
Requires-Python: >=3.9
Requires-Dist: graphviz==0.20.*
Requires-Dist: matplotlib==3.8.*
Requires-Dist: networkx==3.2.*
Requires-Dist: pydantic==2.6.*
Requires-Dist: pydot>=2
Requires-Dist: tk
